kedro_databricks/__init__.py
kedro_databricks/bundle.py
kedro_databricks/deploy.py
kedro_databricks/init.py
kedro_databricks/plugin.py
kedro_databricks/run.py
kedro_databricks/utils.py
kedro_databricks_dev-0.1.2.dist-info/METADATA
kedro_databricks_dev-0.1.2.dist-info/WHEEL
kedro_databricks_dev-0.1.2.dist-info/entry_points.txt
kedro_databricks_dev-0.1.2.dist-info/licenses/LICENSE
kedro_databricks_dev-0.1.2.dist-info/RECORD
