Metadata-Version: 2.3
Name: kedro-databricks-dev
Version: 0.1.2
Summary: A plugin to run Kedro pipelines on Databricks
Project-URL: Homepage, https://github.com/jenspederm/kedro-databricks
Project-URL: Issues, https://github.com/jenspederm/kedro-databricks/issues
Author-email: Jens Peder Meldgaard <jenspederm@gmail.com>
License-File: LICENSE
Requires-Python: >=3.8
Requires-Dist: kedro>=0.19.0
Requires-Dist: mergedeep>=1.3.4
